xia_engine/__init__.py
xia_engine/acl.cpython-310-darwin.so
xia_engine/base.cpython-310-darwin.so
xia_engine/document.cpython-310-darwin.so
xia_engine/engine.cpython-310-darwin.so
xia_engine/exception.cpython-310-darwin.so
xia_engine/fields.cpython-310-darwin.so
xia_engine-0.8.59.dist-info/LICENSE.txt
xia_engine-0.8.59.dist-info/METADATA
xia_engine-0.8.59.dist-info/WHEEL
xia_engine-0.8.59.dist-info/top_level.txt
xia_engine-0.8.59.dist-info/RECORD
