Metadata-Version: 2.1
Name: xia-engine
Version: 0.8.59
Summary: UNKNOWN
Home-page: https://develop.x-i-a.com/docs/xia-engine/0.8.59/index.html
Author: X-I-A
Author-email: admin@x-i-a.com
License: UNKNOWN
Platform: UNKNOWN
Requires-Python: >=3.9
License-File: LICENSE.txt
Requires-Dist: xia-fields
